[
    {
        "name": "architecture",
        "size": 4984,
        "timestamp": 1769220057.4861634,
        "utc": "2026-01-24T02:00:57.486163+00:00",
        "hash": "f04f55f873ba6ccf6040c679a9c412483b160a3c5458561ecd93efff3c8d3fbc",
        "path": "https://tsypuk.github.io/aws-news/news/architecture.json"
    },
    {
        "name": "aws_cost_management",
        "size": 2,
        "timestamp": 1769220057.5551631,
        "utc": "2026-01-24T02:00:57.555163+00:00",
        "hash": "4f53cda18c2baa0c0354bb5f9a3ecbe5ed12ab4d8e11ba873c2f11161202b945",
        "path": "https://tsypuk.github.io/aws-news/news/aws_cost_management.json"
    },
    {
        "name": "aws_partner_network",
        "size": 4677,
        "timestamp": 1769220057.8991625,
        "utc": "2026-01-24T02:00:57.899163+00:00",
        "hash": "ce75464e77a903f5d8f6d9bc1beb688cc273c90baf00c80da0ebcbf13b2a7bb1",
        "path": "https://tsypuk.github.io/aws-news/news/aws_partner_network.json"
    },
    {
        "name": "aws_marketplace",
        "size": 5072,
        "timestamp": 1769220058.141162,
        "utc": "2026-01-24T02:00:58.141162+00:00",
        "hash": "90103a2af264dcb58cd264c4a311e7b1a2d8fb335a0eeb1794ca914d76d98e6f",
        "path": "https://tsypuk.github.io/aws-news/news/aws_marketplace.json"
    },
    {
        "name": "aws_news",
        "size": 5468,
        "timestamp": 1769220058.3731616,
        "utc": "2026-01-24T02:00:58.373162+00:00",
        "hash": "9c4e3634196ef5c8e775bec0085db44b1b5833193b8345f19ec0c1d0359045c8",
        "path": "https://tsypuk.github.io/aws-news/news/aws_news.json"
    },
    {
        "name": "big_data",
        "size": 5264,
        "timestamp": 1769220058.7511606,
        "utc": "2026-01-24T02:00:58.751161+00:00",
        "hash": "8992bc7aaa82c890d76b4aa3a37ffd53e62f8d0f73916f885b17fc154b1dde81",
        "path": "https://tsypuk.github.io/aws-news/news/big_data.json"
    },
    {
        "name": "business_productivity",
        "size": 4911,
        "timestamp": 1769220058.9171603,
        "utc": "2026-01-24T02:00:58.917160+00:00",
        "hash": "8f5bf1ba091017b2367fcdfa7ba4ab026041ac9b90a2b3cf2135a76fb8af4c48",
        "path": "https://tsypuk.github.io/aws-news/news/business_productivity.json"
    },
    {
        "name": "compute",
        "size": 4658,
        "timestamp": 1769220059.1951597,
        "utc": "2026-01-24T02:00:59.195160+00:00",
        "hash": "93a5250f7b60cb9c5d6e612e630898897029a6198daa69dfb36b70f9305fc3f0",
        "path": "https://tsypuk.github.io/aws-news/news/compute.json"
    },
    {
        "name": "contact_center",
        "size": 4976,
        "timestamp": 1769220059.5081596,
        "utc": "2026-01-24T02:00:59.508160+00:00",
        "hash": "45903293f82cf43e208b9d9311ede59227fb1d2ce6215890dee8be2996d18a87",
        "path": "https://tsypuk.github.io/aws-news/news/contact_center.json"
    },
    {
        "name": "containers",
        "size": 2453,
        "timestamp": 1769220059.7091599,
        "utc": "2026-01-24T02:00:59.709160+00:00",
        "hash": "fb7f6b30de5c4e602d5d467e683cd1d592e6047e02d9c89c5a0c9dc19ce3efd1",
        "path": "https://tsypuk.github.io/aws-news/news/containers.json"
    },
    {
        "name": "database",
        "size": 5035,
        "timestamp": 1769220060.0321598,
        "utc": "2026-01-24T02:01:00.032160+00:00",
        "hash": "194b7144637ac7cd68890f7d1fcfb00b4866fa43928c6648d9dfe313b549496f",
        "path": "https://tsypuk.github.io/aws-news/news/database.json"
    },
    {
        "name": "desktop_and_application_streaming",
        "size": 5534,
        "timestamp": 1769220060.1971598,
        "utc": "2026-01-24T02:01:00.197160+00:00",
        "hash": "e31473e36340ff8a9a915c1d13b3e417ec63fdc2bb54e3725c8df9fe9c3ca382",
        "path": "https://tsypuk.github.io/aws-news/news/desktop_and_application_streaming.json"
    },
    {
        "name": "developer",
        "size": 4277,
        "timestamp": 1769220060.37516,
        "utc": "2026-01-24T02:01:00.375160+00:00",
        "hash": "f27b77acefe1c29fe876b68356602ccc88b9ac410e5f30f2eeffb4e3a1881c62",
        "path": "https://tsypuk.github.io/aws-news/news/developer.json"
    },
    {
        "name": "devops",
        "size": 4955,
        "timestamp": 1769220060.63516,
        "utc": "2026-01-24T02:01:00.635160+00:00",
        "hash": "6553d5fc08446cbd098503ab6fc77166fadcb7bb6c5fce6008760108c35b7009",
        "path": "https://tsypuk.github.io/aws-news/news/devops.json"
    },
    {
        "name": "enterprise_strategy",
        "size": 4587,
        "timestamp": 1769220060.79416,
        "utc": "2026-01-24T02:01:00.794160+00:00",
        "hash": "712d622e8ca633025ede38ca867a2297d4ed039b0423ce7409482be2a36363a0",
        "path": "https://tsypuk.github.io/aws-news/news/enterprise_strategy.json"
    },
    {
        "name": "front-end_web_mobile",
        "size": 4521,
        "timestamp": 1769220061.05016,
        "utc": "2026-01-24T02:01:01.050160+00:00",
        "hash": "f91543184ce56ac6e7ab51401b531f37c90f522b07021cfa04bbf66c3a147a8a",
        "path": "https://tsypuk.github.io/aws-news/news/front-end_web_mobile.json"
    },
    {
        "name": "game_tech",
        "size": 4375,
        "timestamp": 1769220061.29616,
        "utc": "2026-01-24T02:01:01.296160+00:00",
        "hash": "23669b5eefa9c0e0fb033760b8b909c1ce3d15d202fb587be85f8ba0e94197ba",
        "path": "https://tsypuk.github.io/aws-news/news/game_tech.json"
    },
    {
        "name": "hpc",
        "size": 4679,
        "timestamp": 1769220061.5101602,
        "utc": "2026-01-24T02:01:01.510160+00:00",
        "hash": "446edff936428f83030b602efe89628a0ec807c7176b97107aeb0be7b010739d",
        "path": "https://tsypuk.github.io/aws-news/news/hpc.json"
    },
    {
        "name": "infra_and_automation",
        "size": 5380,
        "timestamp": 1769220061.83416,
        "utc": "2026-01-24T02:01:01.834160+00:00",
        "hash": "8478dc86f558c9c9809b67b7a31a42cc04cc982f999e7b50196c65772be7958d",
        "path": "https://tsypuk.github.io/aws-news/news/infra_and_automation.json"
    },
    {
        "name": "industries",
        "size": 2526,
        "timestamp": 1769220061.99516,
        "utc": "2026-01-24T02:01:01.995160+00:00",
        "hash": "39544e16f742041aa1df6fb6f386757c4b19c16fb8b2c70f3f77760eb7f217e1",
        "path": "https://tsypuk.github.io/aws-news/news/industries.json"
    },
    {
        "name": "internet_of_things",
        "size": 4815,
        "timestamp": 1769220062.2961602,
        "utc": "2026-01-24T02:01:02.296160+00:00",
        "hash": "48598ec4da7c4823059132fed20cf72fa1a31eb52b2cd233ecb6b6b4e5fb9845",
        "path": "https://tsypuk.github.io/aws-news/news/internet_of_things.json"
    },
    {
        "name": "machine_learning",
        "size": 5246,
        "timestamp": 1769220062.5971603,
        "utc": "2026-01-24T02:01:02.597160+00:00",
        "hash": "f8377a4f3b83ef8a03d9b97cf218e698c15e32c799f1ed97455cfb5bbea42aaa",
        "path": "https://tsypuk.github.io/aws-news/news/machine_learning.json"
    },
    {
        "name": "media",
        "size": 4597,
        "timestamp": 1769220062.8311603,
        "utc": "2026-01-24T02:01:02.831160+00:00",
        "hash": "15aecbab616e15a2ef09c7b28fe6aec4b48a6e1c88ce704db48bde49cc03dc55",
        "path": "https://tsypuk.github.io/aws-news/news/media.json"
    },
    {
        "name": "messaging_and_targeting",
        "size": 5062,
        "timestamp": 1769220063.1541605,
        "utc": "2026-01-24T02:01:03.154160+00:00",
        "hash": "9052099162bad8bbf2c22814ed570231c08ad1c22ce51827e25803fea8f47d22",
        "path": "https://tsypuk.github.io/aws-news/news/messaging_and_targeting.json"
    },
    {
        "name": "networking_and_content_delivery",
        "size": 5404,
        "timestamp": 1769220063.4231598,
        "utc": "2026-01-24T02:01:03.423160+00:00",
        "hash": "b76e62653060ce45dbfc0b5b4780adf6b22c8b3a542fe7c939d561349d0831b3",
        "path": "https://tsypuk.github.io/aws-news/news/networking_and_content_delivery.json"
    },
    {
        "name": "open_source",
        "size": 4696,
        "timestamp": 1769220063.6221595,
        "utc": "2026-01-24T02:01:03.622159+00:00",
        "hash": "f7e2d4073e9d87c91196d2a8bdeb0bfb40fd0ccdce0e5c2a8aac33b22c66c502",
        "path": "https://tsypuk.github.io/aws-news/news/open_source.json"
    },
    {
        "name": "public_sector",
        "size": 5017,
        "timestamp": 1769220063.825159,
        "utc": "2026-01-24T02:01:03.825159+00:00",
        "hash": "d45e868355ad17067da439a3a184e9c5b3b281600f896d901b38e4b724bed844",
        "path": "https://tsypuk.github.io/aws-news/news/public_sector.json"
    },
    {
        "name": "quantum_computing",
        "size": 2708,
        "timestamp": 1769220064.0111587,
        "utc": "2026-01-24T02:01:04.011159+00:00",
        "hash": "8432ecbdcc3941c9780aa799f8094ea28ad305b915d0d93b1d97fc55c842247c",
        "path": "https://tsypuk.github.io/aws-news/news/quantum_computing.json"
    },
    {
        "name": "robotics",
        "size": 2150,
        "timestamp": 1769220064.1681583,
        "utc": "2026-01-24T02:01:04.168158+00:00",
        "hash": "baf4e5670c7101132337b97f24607d3dd8939192f492050db99ca4b06cb941aa",
        "path": "https://tsypuk.github.io/aws-news/news/robotics.json"
    },
    {
        "name": "sap",
        "size": 5375,
        "timestamp": 1769220064.394158,
        "utc": "2026-01-24T02:01:04.394158+00:00",
        "hash": "f81d548e7c9bf0f8e54dd48656cb2ccf3fe664bfa4036066376e12d024a5f930",
        "path": "https://tsypuk.github.io/aws-news/news/sap.json"
    },
    {
        "name": "security_identity_complience",
        "size": 5028,
        "timestamp": 1769220064.7201571,
        "utc": "2026-01-24T02:01:04.720157+00:00",
        "hash": "73b61b2aff7ab3862e998e76bf1368d4bb57953da916306624cc08f116b94ff5",
        "path": "https://tsypuk.github.io/aws-news/news/security_identity_complience.json"
    },
    {
        "name": "startups",
        "size": 89681,
        "timestamp": 1769220066.4071536,
        "utc": "2026-01-24T02:01:06.407154+00:00",
        "hash": "40f2041abb7a97afa8c25e253657dc77ea8259f19162dd3924598ff190c09cba",
        "path": "https://tsypuk.github.io/aws-news/news/startups.json"
    },
    {
        "name": "storage",
        "size": 4987,
        "timestamp": 1769220066.708153,
        "utc": "2026-01-24T02:01:06.708153+00:00",
        "hash": "9f681dc48d309b3740661de8abb6fd0221a948d34d162879b46418539006d763",
        "path": "https://tsypuk.github.io/aws-news/news/storage.json"
    },
    {
        "name": "training_certification",
        "size": 2439,
        "timestamp": 1769220066.8321528,
        "utc": "2026-01-24T02:01:06.832153+00:00",
        "hash": "0125b85be0bb93b53f7c5b89a78febdf6b696bf36299206446e71e20a3ac0482",
        "path": "https://tsypuk.github.io/aws-news/news/training_certification.json"
    },
    {
        "name": "windows_on_aws",
        "size": 2561,
        "timestamp": 1769220067.0331523,
        "utc": "2026-01-24T02:01:07.033152+00:00",
        "hash": "a10b0a24bb0e3ce6013c92ba19716edbdd9fe373e93d438f6cdf0082816dbf4d",
        "path": "https://tsypuk.github.io/aws-news/news/windows_on_aws.json"
    }
]