[
    {
        "name": "architecture",
        "size": 4583,
        "timestamp": 1710292169.9979765,
        "utc": "2024-03-13T01:09:29.997977+00:00",
        "hash": "f221b090600d73ee02f3e7009529620762dfe382966012b819a109e948e51bbc",
        "path": "https://blog.tsypuk.com/aws-news/news/architecture.json"
    },
    {
        "name": "aws_cost_management",
        "size": 2,
        "timestamp": 1710292170.0619774,
        "utc": "2024-03-13T01:09:30.061977+00:00",
        "hash": "4f53cda18c2baa0c0354bb5f9a3ecbe5ed12ab4d8e11ba873c2f11161202b945",
        "path": "https://blog.tsypuk.com/aws-news/news/aws_cost_management.json"
    },
    {
        "name": "aws_partner_network",
        "size": 4913,
        "timestamp": 1710292170.509983,
        "utc": "2024-03-13T01:09:30.509983+00:00",
        "hash": "6703383ab6bb0044e362e11e93f95509c0f3c3ad87bed66a6c7e83171c3f23f4",
        "path": "https://blog.tsypuk.com/aws-news/news/aws_partner_network.json"
    },
    {
        "name": "aws_marketplace",
        "size": 4843,
        "timestamp": 1710292170.8939872,
        "utc": "2024-03-13T01:09:30.893987+00:00",
        "hash": "e96c25782c8062431a57091af1e3f95176a4116ef48b2c14083bc79c01f04838",
        "path": "https://blog.tsypuk.com/aws-news/news/aws_marketplace.json"
    },
    {
        "name": "aws_news",
        "size": 5352,
        "timestamp": 1710292171.15399,
        "utc": "2024-03-13T01:09:31.153990+00:00",
        "hash": "8b2f3117e61867795038965ab9ae1e2c2bc77e96b00be4e55f4d624c7c3012c8",
        "path": "https://blog.tsypuk.com/aws-news/news/aws_news.json"
    },
    {
        "name": "big_data",
        "size": 5106,
        "timestamp": 1710292171.6539955,
        "utc": "2024-03-13T01:09:31.653996+00:00",
        "hash": "5d3d96c78abe753b758b90d665d833344c11c5535b08f2a371f5c996d34d8f04",
        "path": "https://blog.tsypuk.com/aws-news/news/big_data.json"
    },
    {
        "name": "business_productivity",
        "size": 5281,
        "timestamp": 1710292171.969999,
        "utc": "2024-03-13T01:09:31.969999+00:00",
        "hash": "170720322fae9253c6c5296a7c40ab82bac64661f133c2b1a972235cc22d63a0",
        "path": "https://blog.tsypuk.com/aws-news/news/business_productivity.json"
    },
    {
        "name": "compute",
        "size": 4349,
        "timestamp": 1710292172.3300035,
        "utc": "2024-03-13T01:09:32.330003+00:00",
        "hash": "c8936a966bf7e5f715f239b5ba5ed17336246c1d01d6b66a4d5847d723debcda",
        "path": "https://blog.tsypuk.com/aws-news/news/compute.json"
    },
    {
        "name": "contact_center",
        "size": 4826,
        "timestamp": 1710292172.6540074,
        "utc": "2024-03-13T01:09:32.654007+00:00",
        "hash": "65fed9379facb873792d7ab62737c8af2020f3dc684306d261853acb0fe92013",
        "path": "https://blog.tsypuk.com/aws-news/news/contact_center.json"
    },
    {
        "name": "containers",
        "size": 2280,
        "timestamp": 1710292172.950011,
        "utc": "2024-03-13T01:09:32.950011+00:00",
        "hash": "b2fb5112f4c68b3bc6476bcd051e35316393d5a933eb6be511580371332f1080",
        "path": "https://blog.tsypuk.com/aws-news/news/containers.json"
    },
    {
        "name": "database",
        "size": 5234,
        "timestamp": 1710292173.3540158,
        "utc": "2024-03-13T01:09:33.354016+00:00",
        "hash": "e70ecab64f16c37d9bc17c4ad3e37ca3c09607db1d8250ac6714885b2ea23309",
        "path": "https://blog.tsypuk.com/aws-news/news/database.json"
    },
    {
        "name": "desktop_and_application_streaming",
        "size": 5045,
        "timestamp": 1710292173.68202,
        "utc": "2024-03-13T01:09:33.682020+00:00",
        "hash": "7c923e62b6d2bf0bda8caada4f640448caa5825024faac296cef8ee0b8594037",
        "path": "https://blog.tsypuk.com/aws-news/news/desktop_and_application_streaming.json"
    },
    {
        "name": "developer",
        "size": 4511,
        "timestamp": 1710292173.9380229,
        "utc": "2024-03-13T01:09:33.938023+00:00",
        "hash": "46bebf576cfceb91f62f4525e436bc934733d765f775927d313a6628af9340f6",
        "path": "https://blog.tsypuk.com/aws-news/news/developer.json"
    },
    {
        "name": "devops",
        "size": 4125,
        "timestamp": 1710292174.3180275,
        "utc": "2024-03-13T01:09:34.318027+00:00",
        "hash": "e80cfdcd8aa4d575d8ec074840bfb94aab08e108e63d2ab2e17dc2b1d64bc34d",
        "path": "https://blog.tsypuk.com/aws-news/news/devops.json"
    },
    {
        "name": "enterprise_strategy",
        "size": 4190,
        "timestamp": 1710292174.5540304,
        "utc": "2024-03-13T01:09:34.554030+00:00",
        "hash": "e11989fcb01d75953e87e6ee886dcb33bed9ba15eaac5d7fc5a8cf687f71f62a",
        "path": "https://blog.tsypuk.com/aws-news/news/enterprise_strategy.json"
    },
    {
        "name": "front-end_web_mobile",
        "size": 4291,
        "timestamp": 1710292175.010036,
        "utc": "2024-03-13T01:09:35.010036+00:00",
        "hash": "88ead5f17a72216e85ca83609177a7c0137a3d5f548b857731ff9b4dd5426cbd",
        "path": "https://blog.tsypuk.com/aws-news/news/front-end_web_mobile.json"
    },
    {
        "name": "game_tech",
        "size": 4750,
        "timestamp": 1710292175.3940406,
        "utc": "2024-03-13T01:09:35.394041+00:00",
        "hash": "0f2586fdfa29d96f14512b9aed9efd11caa7dea29cfb3fd32002ef8271c35dda",
        "path": "https://blog.tsypuk.com/aws-news/news/game_tech.json"
    },
    {
        "name": "hpc",
        "size": 4730,
        "timestamp": 1710292175.7180445,
        "utc": "2024-03-13T01:09:35.718045+00:00",
        "hash": "0c8ad815e8aad142f39dbfd977143c2f4fbd0506ec3fe2cc9d609d2f8d017be1",
        "path": "https://blog.tsypuk.com/aws-news/news/hpc.json"
    },
    {
        "name": "infra_and_automation",
        "size": 4965,
        "timestamp": 1710292176.3060517,
        "utc": "2024-03-13T01:09:36.306052+00:00",
        "hash": "3db24b3e886291da855220213b516f4e8e172f6ebb31b03860a24d789182828d",
        "path": "https://blog.tsypuk.com/aws-news/news/infra_and_automation.json"
    },
    {
        "name": "industries",
        "size": 2327,
        "timestamp": 1710292176.5180542,
        "utc": "2024-03-13T01:09:36.518054+00:00",
        "hash": "0612db333acebaef3b0f2b7434a109cd0db9533182af111c97ae8258057eefae",
        "path": "https://blog.tsypuk.com/aws-news/news/industries.json"
    },
    {
        "name": "internet_of_things",
        "size": 4609,
        "timestamp": 1710292176.9900599,
        "utc": "2024-03-13T01:09:36.990060+00:00",
        "hash": "751ac91ab2ee856aa2f75a95ce242a88f12dead1da793e2bfd841fe5e949de23",
        "path": "https://blog.tsypuk.com/aws-news/news/internet_of_things.json"
    },
    {
        "name": "machine_learning",
        "size": 5277,
        "timestamp": 1710292177.410065,
        "utc": "2024-03-13T01:09:37.410065+00:00",
        "hash": "35328d4c4b8d3dfb10a31c4b9e64dcb68b859acd2f1b06baa62aa238ae9016b1",
        "path": "https://blog.tsypuk.com/aws-news/news/machine_learning.json"
    },
    {
        "name": "media",
        "size": 4765,
        "timestamp": 1710292177.8220701,
        "utc": "2024-03-13T01:09:37.822070+00:00",
        "hash": "558b3fe3d48179218bfafc48b568c1e0e1b23c694a739dfc5e79dc7a87a82f55",
        "path": "https://blog.tsypuk.com/aws-news/news/media.json"
    },
    {
        "name": "messaging_and_targeting",
        "size": 4533,
        "timestamp": 1710292178.3300762,
        "utc": "2024-03-13T01:09:38.330076+00:00",
        "hash": "55105a8b800c7c047786f7cb826104546aaf4ce859e6975b65ccdcecb9a142f4",
        "path": "https://blog.tsypuk.com/aws-news/news/messaging_and_targeting.json"
    },
    {
        "name": "networking_and_content_delivery",
        "size": 5184,
        "timestamp": 1710292178.810082,
        "utc": "2024-03-13T01:09:38.810082+00:00",
        "hash": "01faacc0c322cb01701f3a7b27eff71c714db1bb7bb9dac5b99e10e9a65b7d97",
        "path": "https://blog.tsypuk.com/aws-news/news/networking_and_content_delivery.json"
    },
    {
        "name": "open_source",
        "size": 4487,
        "timestamp": 1710292179.1220858,
        "utc": "2024-03-13T01:09:39.122086+00:00",
        "hash": "8580b923528bb9fc5f16cb3ef6b93ad95d820db12fd5e2c83c73f29a3d704c51",
        "path": "https://blog.tsypuk.com/aws-news/news/open_source.json"
    },
    {
        "name": "public_sector",
        "size": 4879,
        "timestamp": 1710292179.382089,
        "utc": "2024-03-13T01:09:39.382089+00:00",
        "hash": "511c5a3cf5a044b3919680a448277f5e4ff69d5c3c44c0af37630296779e281d",
        "path": "https://blog.tsypuk.com/aws-news/news/public_sector.json"
    },
    {
        "name": "quantum_computing",
        "size": 2753,
        "timestamp": 1710292179.638092,
        "utc": "2024-03-13T01:09:39.638092+00:00",
        "hash": "4fab3d7c1e1c99f6a70c161156a4f2f8d12575b69bcf94f6601051cce4b5a21f",
        "path": "https://blog.tsypuk.com/aws-news/news/quantum_computing.json"
    },
    {
        "name": "robotics",
        "size": 2150,
        "timestamp": 1710292179.8340945,
        "utc": "2024-03-13T01:09:39.834095+00:00",
        "hash": "baf4e5670c7101132337b97f24607d3dd8939192f492050db99ca4b06cb941aa",
        "path": "https://blog.tsypuk.com/aws-news/news/robotics.json"
    },
    {
        "name": "sap",
        "size": 4392,
        "timestamp": 1710292180.2221007,
        "utc": "2024-03-13T01:09:40.222101+00:00",
        "hash": "f8e0993924cf0eb1d5630c2628643c1e8aaa67ec75e7d077f0da7dad1c5e83d6",
        "path": "https://blog.tsypuk.com/aws-news/news/sap.json"
    },
    {
        "name": "security_identity_complience",
        "size": 4748,
        "timestamp": 1710292180.6341076,
        "utc": "2024-03-13T01:09:40.634108+00:00",
        "hash": "a4f3ff841fcff5a259f700d8c5b23c29592369403144bd015843cfb30206f29c",
        "path": "https://blog.tsypuk.com/aws-news/news/security_identity_complience.json"
    },
    {
        "name": "startups",
        "size": 89212,
        "timestamp": 1710292182.978146,
        "utc": "2024-03-13T01:09:42.978146+00:00",
        "hash": "1153c3c846b3e203437bb4e61a8c7252231a996506e3f466db34c1e27fc8ee6d",
        "path": "https://blog.tsypuk.com/aws-news/news/startups.json"
    },
    {
        "name": "storage",
        "size": 4993,
        "timestamp": 1710292183.442152,
        "utc": "2024-03-13T01:09:43.442152+00:00",
        "hash": "b55b4808cd7a120e8efdb01f451e3979d154e62bcb4e5df77361517421c18874",
        "path": "https://blog.tsypuk.com/aws-news/news/storage.json"
    },
    {
        "name": "training_certification",
        "size": 2256,
        "timestamp": 1710292183.618154,
        "utc": "2024-03-13T01:09:43.618154+00:00",
        "hash": "c68b634309b82a9eb55b9dc78842bec7c72654471b0ed15b173407c98693b7a5",
        "path": "https://blog.tsypuk.com/aws-news/news/training_certification.json"
    },
    {
        "name": "windows_on_aws",
        "size": 2475,
        "timestamp": 1710292183.9141574,
        "utc": "2024-03-13T01:09:43.914157+00:00",
        "hash": "500f7ca6ce36020826ac2671ca055294404618592628240ce32eb29a8c92cde0",
        "path": "https://blog.tsypuk.com/aws-news/news/windows_on_aws.json"
    }
]